interegular/__init__.py
interegular/comparator.py
interegular/fsm.py
interegular/patterns.py
interegular/py.typed
interegular/utils/__init__.py
interegular/utils/simple_parser.py
interegular-0.3.2.dist-info/LICENSE.txt
interegular-0.3.2.dist-info/METADATA
interegular-0.3.2.dist-info/WHEEL
interegular-0.3.2.dist-info/top_level.txt
interegular-0.3.2.dist-info/RECORD
