Metadata-Version: 2.1
Name: interegular
Version: 0.3.2
Summary: a regex intersection checker
Home-page: https://github.com/MegaIng/regex_intersections
Download-URL: https://github.com/MegaIng/interegular/tarball/master
Author: MegaIng
Author-email: MegaIng <trampchamp@hotmail.de>
License: MIT
Classifier: Operating System :: OS Independent
Classifier: License :: OSI Approved :: MIT License
Classifier: Programming Language :: Python :: 3 :: Only
Classifier: Programming Language :: Python :: 3.6
Classifier: Programming Language :: Python :: 3.7
Classifier: Programming Language :: Python :: 3.8
Classifier: Programming Language :: Python :: 3.9
Requires-Python: >=3.6
License-File: LICENSE.txt
Requires-Dist: dataclasses ; python_version < "3.7"
